cordic_vectoring.v
`timescale 1 ns/100 ps


module sublime(clock, angle, xin, yin, xout, yout);

parameter xy_size = 8;
localparam STG = xy_size;

input clock;
input signed [31:0] angle;
input signed [xy_size-1:0] xin;
input signed [xy_size-1:0] yin;
output signed [xy_size-1:0] xout;
output signed [xy_size-1:0] yout;


wire signed [31:0] atan_table [0:30];

	assign atan_table[00] = 32'b00100000000000000000000000000000; // 45.000 degrees -> atan(2^0)
  	assign atan_table[01] = 32'b00010010111001000000010100011101; // 26.565 degrees -> atan(2^-1)
	assign atan_table[02] = 32'b00001001111110110011100001011011; // 14.036 degrees -> atan(2^-2)
	assign atan_table[03] = 32'b00000101000100010001000111010100; // atan(2^-3)
	assign atan_table[04] = 32'b00000010100010110000110101000011;
	assign atan_table[05] = 32'b00000001010001011101011111100001;
	assign atan_table[06] = 32'b00000000101000101111011000011110;
	assign atan_table[07] = 32'b00000000010100010111110001010101;
	assign atan_table[08] = 32'b00000000001010001011111001010011;
/*	
	assign atan_table[09] = 32'b00000000000101000101111100101110;
	assign atan_table[10] = 32'b00000000000010100010111110011000;
	assign atan_table[11] = 32'b00000000000001010001011111001100;
	assign atan_table[12] = 32'b00000000000000101000101111100110;
	assign atan_table[13] = 32'b00000000000000010100010111110011;
	assign atan_table[14] = 32'b00000000000000001010001011111001;
	assign atan_table[15] = 32'b00000000000000000101000101111101;
	assign atan_table[16] = 32'b00000000000000000010100010111110;
	assign atan_table[17] = 32'b00000000000000000001010001011111;
	assign atan_table[18] = 32'b00000000000000000000101000101111;
	assign atan_table[19] = 32'b00000000000000000000010100011000;
	assign atan_table[20] = 32'b00000000000000000000001010001100;
	assign atan_table[21] = 32'b00000000000000000000000101000110;
	assign atan_table[22] = 32'b00000000000000000000000010100011;
	assign atan_table[23] = 32'b00000000000000000000000001010001;
	assign atan_table[24] = 32'b00000000000000000000000000101000;
	assign atan_table[25] = 32'b00000000000000000000000000010100;
	assign atan_table[26] = 32'b00000000000000000000000000001010;
	assign atan_table[27] = 32'b00000000000000000000000000000101;
	assign atan_table[28] = 32'b00000000000000000000000000000010;
	assign atan_table[29] = 32'b00000000000000000000000000000001;
	assign atan_table[30] = 32'b00000000000000000000000000000000;
*/

// --------------- //
//    registers    //
// --------------- //

reg signed [xy_size:0] x [0:STG-1];
reg signed [xy_size:0] y [0:STG-1];
reg signed [31:0] z [0:STG-1];

// ------------------------ //
//          stage 0         //
// ------------------------ //

wire [1:0] quadrant;
assign quadrant = angle[31:30];

always @(posedge clock) 
begin // make sure the rotation angle is in the -pi/2 to pi/2 range. If not then pre-rotate
	case (quadrant)
		2'b00,
		2'b11:
		begin  
			x[0] <= xin;
			y[0] <= yin;
			z[0] <= angle;
		end
		2'b01:
		begin
			x[0] <= -yin;
			y[0] <= xin;
			z[0] <= {2'b00,angle[29:0]}; // sub pi/2 from angle for this quadrant
		end
		2'b10:
		begin
			x[0] <= yin;
			y[0] <= -xin;
			z[0] <= {2'b11,angle[29:0]}; // add pi/2 to angle for this quadrant
		end
	endcase
end

// --------------------------------------------- //
//          generate stages 1 to STG - 1         //
// --------------------------------------------- //
generate
genvar i;
for(i=0; i < (STG-1); i=i+1)
begin: xyz

	wire z_sign;
	wire signed [xy_size:0] x_shr, y_shr;

	assign x_shr = x[i] >>> i; // signed shift right
	assign y_shr = y[i] >>> i;

	assign z_sign = z[i][31];

	always @(posedge clock)
	begin
		// add/sub shifted data
		x[i+1] <= z_sign ? x[i] + y_shr : x[i] - y_shr;
		y[i+1] <= z_sign ? y[i] - x_shr : y[i] + x_shr;
		z[i+1] <= z_sign ? z[i] + atan_table[i] : z[i] - atan_table[i];
	end
end
endgenerate

assign xout = x[STG-1];
assign yout = y[STG-1];

endmodule

cordic_vectoring_tb.v

module sublime_tb;
parameter  xy_size = 8;
localparam STG = xy_size;

reg clock;
reg [31:0] angle;
reg [xy_size-1:0] xin;
reg [xy_size-1:0] yin;
reg signed [63:0] i;

wire [xy_size-1:0] xout;
wire [xy_size-1:0] yout;

localparam An = 32000/1.647;

initial 
begin
	$dumpfile("cordic.vcd");
	$dumpvars;
	angle = 32'b00110101010101010101010101010101;
	xin = An;
	yin = 0;

	clock = 0;

	#1000
	angle = 32'b00100000000000000000000000000000;

	#1000
	$write("Simulation has finished");
	$stop;
end
always #10 clock = !clock;
sublime s(
		.clock(clock),
 		.angle(angle),
 		.xin(xin),
 		.yin(yin),
 		.xout(xout),
 		.yout(yout)
 		);

initial 
	$monitor($time," clock=%d, angle=%d, xin=%d, yin=%d, xout=%d, yout=%d", clock, angle, xin, yin, xout, yout);
endmodule

cordic.vcd
$date
	Tue Jul 18 20:50:52 2017
$end
$version
	Icarus Verilog
$end
$timescale
	100ps
$end
$scope module sublime_tb $end
$var wire 8 ! yout [7:0] $end
$var wire 8 " xout [7:0] $end
$var reg 32 # angle [31:0] $end
$var reg 1 $ clock $end
$var reg 8 % xin [7:0] $end
$var reg 8 & yin [7:0] $end
$scope module s $end
$var wire 32 ' angle [31:0] $end
$var wire 1 $ clock $end
$var wire 8 ( xin [7:0] $end
$var wire 8 ) yin [7:0] $end
$var wire 8 * yout [7:0] $end
$var wire 8 + xout [7:0] $end
$var wire 2 , quadrant [1:0] $end
$scope begin xyz[0] $end
$var wire 9 - x_shr [8:0] $end
$var wire 9 . y_shr [8:0] $end
$var wire 1 / z_sign $end
$upscope $end
$scope begin xyz[1] $end
$var wire 1 0 z_sign $end
$var wire 9 1 y_shr [8:0] $end
$var wire 9 2 x_shr [8:0] $end
$upscope $end
$scope begin xyz[2] $end
$var wire 1 3 z_sign $end
$var wire 9 4 y_shr [8:0] $end
$var wire 9 5 x_shr [8:0] $end
$upscope $end
$scope begin xyz[3] $end
$var wire 1 6 z_sign $end
$var wire 9 7 y_shr [8:0] $end
$var wire 9 8 x_shr [8:0] $end
$upscope $end
$scope begin xyz[4] $end
$var wire 1 9 z_sign $end
$var wire 9 : y_shr [8:0] $end
$var wire 9 ; x_shr [8:0] $end
$upscope $end
$scope begin xyz[5] $end
$var wire 1 < z_sign $end
$var wire 9 = y_shr [8:0] $end
$var wire 9 > x_shr [8:0] $end
$upscope $end
$scope begin xyz[6] $end
$var wire 1 ? z_sign $end
$var wire 9 @ y_shr [8:0] $end
$var wire 9 A x_shr [8:0] $end
$upscope $end
$upscope $end
$upscope $end
$enddefinitions $end
#0
$dumpvars
bx A
bx @
x?
bx >
bx =
x<
bx ;
bx :
x9
bx 8
bx 7
x6
bx 5
bx 4
x3
bx 2
bx 1
x0
x/
bx .
bx -
b0 ,
bx +
bx *
b0 )
b11100101 (
b110101010101010101010101010101 '
b0 &
b11100101 %
0$
b110101010101010101010101010101 #
bx "
bx !
$end
#100
0/
b0 .
b111100101 -
1$
#200
0$
#300
00
b111110010 1
b111110010 2
1$
#400
0$
#500
03
b111110101 4
b111111100 5
1$
#600
0$
#700
16
b111111010 7
b111111111 8
1$
#800
0$
#900
19
b111111101 :
b111111111 ;
1$
#1000
0$
#1100
0<
b111111110 =
b111111111 >
1$
#1200
0$
#1300
1?
b111111111 @
b111111111 A
1$
#1400
0$
#1500
b11010101 !
b11010101 *
b11110110 "
b11110110 +
1$
